gramload/__init__.py
gramload/gramload.py
gramload-1.0.0.dist-info/METADATA
gramload-1.0.0.dist-info/WHEEL
gramload-1.0.0.dist-info/entry_points.txt
gramload-1.0.0.dist-info/top_level.txt
gramload-1.0.0.dist-info/RECORD
